unkey.py
unkey-0.0.2.dist-info/LICENSE
unkey-0.0.2.dist-info/METADATA
unkey-0.0.2.dist-info/WHEEL
unkey-0.0.2.dist-info/entry_points.txt
unkey-0.0.2.dist-info/top_level.txt
unkey-0.0.2.dist-info/RECORD
