Metadata-Version: 2.1
Name: unkey
Version: 0.0.2
Summary: A tool to automatically remove extra calls to keys().
Home-page: https://github.com/mxr/unkey
Author: Max R
Author-email: maxr@outlook.com
License: MIT
Classifier: License :: OSI Approved :: MIT License
Classifier: Programming Language :: Python :: 3
Classifier: Programming Language :: Python :: 3 :: Only
Classifier: Programming Language :: Python :: Implementation :: CPython
Classifier: Programming Language :: Python :: Implementation :: PyPy
Requires-Python: >=3.10
License-File: LICENSE
Requires-Dist: tokenize-rt >=3.2.0
